{
    "Choco Truffle":{
    "name": " Choco Truffle",
    "profuction-cost": 9,
    "market-price": 16,
    "produced": 1327,
    "sold": 1302},

             
    "Brown Bar":{
        "name": "Brown Bar",
        "production-cost":7,
        "market-price":15,
        "produced": 1400,
        "sold": 1369},

    "White Bublle": {
        "name":"White Bubble",
        "production-cost":10,
        "market-price":20,
        "produced": 1300,
        "sold": 1294},
    

        "Hazzle Drops":{
            "name": "Hazzle Drops",
            "production-cost": 15,
            "makret-price": 35,
            "produced":1250,
            "sold": 1223},
    
        "Caramel Blast" :{
            "name": "Caramel Blast",
            "production-cost": 4,
            "market-price":10,
            "produced":1600,
            "sold":1597}
    }
        
